Workbook

Sheet README
A1: India EV Charging Infrastructure Intelligence
A2: Data-driven analysis of public charging coverage, station density, and demand-supply mismatch across Indian states
A5: SHEETS IN THIS WORKBOOK
A6: 1. README — this page
A7: 2. OCM_Raw_Data — 1,179 geolocated public charging sites in India, sourced from OpenChargeMap (OCM) via the Open Charge Map API, filtered from a 242,417-site global dataset
A8: 3. State_Summary — station counts, ports, avg power, fast-DC share by state (computed from OCM raw data)
A9: 4. Official_vs_Crowdsourced — official Ministry of Power/PIB station counts benchmarked against OCM's crowdsourced coverage, by state
A10: 5. Demand_Supply_Gap — EV sales volumes vs charging stations, by state, with a stations-per-vehicle stress metric
A11: 6. Recommendations — expansion priority scoring by state
A13: DATA SOURCES (all real, publicly available, cited)
A14: - OpenChargeMap.org / Open Charge Map API (CC BY-SA 4.0) — geolocated station data, accessed via github.com/tarekmasryo/global-ev-infra-dataset
A15: - Press Information Bureau, Govt of India, Ministry of Heavy Industries, 08-Aug-2025 (PRID 2154127) — official national + top-7-state EVCS counts
... A25: - EV sales figures are only available for the 3 states with recent public reporting (Karnataka, Maharashtra, Uttar Pradesh) at the time of writing — this workbook does NOT fabricate numbers for states without a citable source. Blank cells are blank on purpose.

Sheet OCM_Raw_Data
A1: id | B1: name | C1: city | D1: state | E1: country_code | F1: latitude | G1: longitude | H1: ports | I1: power_kw | J1: power_class | K1: is_fast_dc
A2: 460636 | B2: Hotel Kantara Dine | C2: Solur | D2: Karnataka | E2: IN | F2: 13.064574 | G2: 77.257125 | H2: 1 | I2: 30 | J2: AC_HIGH_(22-49kW) | K2: =FALSE() -> FALSE
A3: 460478 | B3: Burger King | C3: Udayapura | D3: Karnataka | E3: IN | F3: 12.960134 | G3: 76.330239 | H3: 1 | I3: 120 | J3: DC_FAST_(50-149kW) | K3: =TRUE() -> TRUE
A4: 460205 | B4: Konnagar | C4: Kolkata | D4: West Bengal | E4: IN | F4: 21.651444 | G4: 87.6514 | H4: 1 | J4: UNKNOWN | K4: =FALSE() -> FALSE
A5: 458918 | B5: Tata.ev Luxon Motors - Tata Power | C5: Edappally | D5: Kerala | E5: IN | F5: 10.011485 | G5: 76.311387 | H5: 2 | I5: 60 | J5: DC_FAST_(50-149kW) | K5: =TRUE() -> TRUE
A6: 458917 | B6: TML Sree Gokulam Motors - Tata Power | C6: Edappally | D6: Kerala | E6: IN | F6: 10.039155 | G6: 76.315559 | H6: 1 | I6: 30 | J6: AC_HIGH_(22-49kW) | K6: =FALSE() -> FALSE
A7: 458916 | B7: Tata.ev Gokulam Motors - Tata Power | C7: Choornikkara | D7: Kerala | E7: IN | F7: 10.081303 | G7: 76.339462 | H7: 1 | I7: 60 | J7: DC_FAST_(50-149kW) | K7: =TRUE() -> TRUE
A8: 458915 | B8: Taj Cochin Internation Airport Hotel - Tata Power | C8: Nedumbassery | D8: Kerala | E8: IN | F8: 10.159995 | G8: 76.390154 | H8: 1 | I8: 30 | J8: AC_HIGH_(22-49kW) | K8: =FALSE() -> FALSE
A9: 458914 | B9: SAJ Earth Resort - Tata Power | C9: Nedumbassery | D9: Kerala | E9: IN | F9: 10.162224 | G9: 76.384653 | H9: 1 | I9: 30 | J9: AC_HIGH_(22-49kW) | K9: =FALSE() -> FALSE
A10: 458913 | B10: Luxon Motors - Tata Power | C10: Kariyad | D10: Kerala | E10: IN | F10: 10.162042 | G10: 76.367356 | H10: 1 | I10: 30 | J10: AC_HIGH_(22-49kW) | K10: =FALSE() -> FALSE
A11: 458912 | B11: Sree Gokulam Motors - Tata Power | C11: Angamaly | D11: Kerala | E11: IN | F11: 10.22106 | G11: 76.376752 | H11: 1 | I11: 30 | J11: AC_HIGH_(22-49kW) | K11: =FALSE() -> FALSE
A12: 458911 | B12: Centro Mall Charging Station - Tata Power | C12: Kodungallur | D12: Kerala | E12: IN | F12: 10.232489 | G12: 76.19594 | H12: 1 | I12: 30 | J12: AC_HIGH_(22-49kW) | K12: =FALSE() -> FALSE
A13: 458910 | B13: IOCL Thiruvonam Fuels - Tata Power | C13: Palakkad | D13: Kerala | E13: IN | F13: 10.769831 | G13: 76.668097 | H13: 2 | I13: 30 | J13: AC_HIGH_(22-49kW) | K13: =FALSE() -> FALSE
A14: 458909 | B14: KVR Automotive - Tata Power | C14: Koppam | D14: Kerala | E14: IN | F14: 10.782258 | G14: 76.658245 | H14: 1 | I14: 30 | J14: AC_HIGH_(22-49kW) | K14: =FALSE() -> FALSE
A15: 458908 | B15: Gokulam Residency - Tata Power | C15: Amballur | D15: Kerala | E15: IN | F15: 10.436187 | G15: 76.265206 | H15: 1 | I15: 25 | J15: AC_HIGH_(22-49kW) | K15: =FALSE() -> FALSE
A16: 458907 | B16: Tata.ev Hyson Motors - Tata Power | C16: Thrissur | D16: Kerala | E16: IN | F16: 10.496728 | G16: 76.258361 | H16: 2 | I16: 60 | J16: DC_FAST_(50-149kW) | K16: =TRUE() -> TRUE
A17: 458906 | B17: PCK Centenary | C17: Thrissur | D17: Kerala | E17: IN | F17: 10.52294 | G17: 76.206248 | H17: 1 | I17: 30 | J17: AC_HIGH_(22-49kW) | K17: =FALSE() -> FALSE
A18: 458905 | B18: TML Hyson Motors - Tata Power | C18: Thrissur | D18: Kerala | E18: IN | F18: 10.540423 | G18: 76.189678 | H18: 2 | I18: 25 | J18: AC_HIGH_(22-49kW) | K18: =FALSE() -> FALSE
A19: 458904 | B19: Hotel Gokulam Sabari - Tata Power | C19: Guruvayur | D19: Kerala | E19: IN | F19: 10.596357 | G19: 76.042934 | H19: 2 | I19: 25 | J19: AC_HIGH_(22-49kW) | K19: =FALSE() -> FALSE
A20: 314018 | B20: Shirdi | C20: Shirdi | D20: Maharashtra | E20: IN | F20: 19.757594 | G20: 74.476347 | H20: 1 | I20: 30 | J20: AC_HIGH_(22-49kW) | K20: =FALSE() -> FALSE
A21: 313995 | B21: InFour Wheel Care And Tyres - Tata Power | C21: Perinthalmanna | D21: Kerala | E21: IN | F21: 10.960238 | G21: 76.234679 | H21: 1 | I21: 25 | J21: AC_HIGH_(22-49kW) | K21: =FALSE() -> FALSE
A22: 313994 | B22: TML KVR Automotive - Tata Power | C22: Perinthalmanna | D22: Kerala | E22: IN | F22: 10.984503 | G22: 76.187847 | H22: 1 | I22: 30 | J22: AC_HIGH_(22-49kW) | K22: =FALSE() -> FALSE
A23: 313993 | B23: IOCL Sigma Enterprises Charging Station - Tata Power | C23: Valanchery | D23: Kerala | E23: IN | F23: 10.897914 | G23: 76.06101 | H23: 1 | I23: 30 | J23: AC_HIGH_(22-49kW) | K23: =FALSE() -> FALSE
A24: 313992 | B24: AAK Mall | C24: Tirur | D24: Kerala | E24: IN | F24: 10.918581 | G24: 75.917798 | H24: 1 | I24: 30 | J24: AC_HIGH_(22-49kW) | K24: =FALSE() -> FALSE
A25: 313991 | B25: Tata.ev Store Malappuram | C25: Malappuram | D25: Kerala | E25: IN | F25: 11.052515 | G25: 76.07764 | H25: 2 | I25: 60 | J25: DC_FAST_(50-149kW) | K25: =TRUE() -> TRUE
A26: 313990 | B26: A M Tyres Malappuram - Tata Power | C26: Malappuram | D26: Kerala | E26: IN | F26: 11.060403 | G26: 76.080844 | H26: 1 | I26: 30 | J26: AC_HIGH_(22-49kW) | K26: =FALSE() -> FALSE
A27: 313989 | B27: Hotel Gokulam Relax Park | C27: Manjeri | D27: Kerala | E27: IN | F27: 11.118906 | G27: 76.118474 | H27: 2 | I27: 25 | J27: AC_HIGH_(22-49kW) | K27: =FALSE() -> FALSE
A28: 313988 | B28: One Stop Automotive Cahrging Station - Tata Power | C28: Edavanna | D28: Kerala | E28: IN | F28: 11.204146 | G28: 76.136734 | H28: 2 | I28: 60 | J28: DC_FAST_(50-149kW) | K28: =TRUE() -> TRUE
A29: 313980 | B29: Moto Town Auto Hub - Tata Power | C29: Wandoor | D29: Kerala | E29: IN | F29: 11.22325 | G29: 76.216915 | H29: 1 | I29: 30 | J29: AC_HIGH_(22-49kW) | K29: =FALSE() -> FALSE
A30: 313979 | B30: IOCL Aaditya Petroleum Naduvath Charging Station - Tata Power | C30: Wandoor | D30: Kerala | E30: IN | F30: 11.211054 | G30: 76.224685 | H30: 1 | I30: 30 | J30: AC_HIGH_(22-49kW) | K30: =FALSE() -> FALSE
A31: 313978 | B31: Calicut Airport Charging Station - Tata Power | C31: Kondotty | D31: Kerala | E31: IN | F31: 11.140292 | G31: 75.948314 | H31: 2 | I31: 60 | J31: DC_FAST_(50-149kW) | K31: =TRUE() -> TRUE
A32: 313955 | B32: TML Marina Motors - Tata Power | C32: Kozhikode | D32: Kerala | E32: IN | F32: 11.216965 | G32: 75.857951 | H32: 2 | I32: 25 | J32: AC_HIGH_(22-49kW) | K32: =FALSE() -> FALSE
A33: 313954 | B33: Rotana Motors Meenchanda - Tata Power | C33: Meenchanda | D33: Kerala | E33: IN | F33: 11.213909 | G33: 75.802632 | H33: 1 | I33: 30 | J33: AC_HIGH_(22-49kW) | K33: =FALSE() -> FALSE
A34: 313953 | B34: IOCL Lakshmi Sales & Service - Tata Power | C34: Kozhikode | D34: Kerala | E34: IN | F34: 11.233627 | G34: 75.803239 | H34: 1 | I34: 30 | J34: AC_HIGH_(22-49kW) | K34: =FALSE() -> FALSE
A35: 313952 | B35: Gokulam Galleria Mall - Tata Power | C35: Kozhikode | D35: Kerala | E35: IN | F35: 11.258465 | G35: 75.792906 | H35: 5 | I35: 25 | J35: AC_HIGH_(22-49kW) | K35: =FALSE() -> FALSE
A36: 313951 | B36: Hotel Hyson Heritage - Tata Power | C36: Kozhikode | D36: Kerala | E36: IN | F36: 11.259214 | G36: 75.779335 | H36: 2 | I36: 25 | J36: AC_HIGH_(22-49kW) | K36: =FALSE() -> FALSE
A37: 313950 | B37: Taj The Gateway Hotel - Tata Power | C37: Kozhikode | D37: Kerala | E37: IN | F37: 11.25869 | G37: 75.773979 | H37: 2 | I37: 30 | J37: AC_HIGH_(22-49kW) | K37: =FALSE() -> FALSE
A38: 313947 | B38: IOCL Engapuzha Fuel - Tata Power | C38: Engapuzha | D38: Kerala | E38: IN | F38: 11.46505 | G38: 75.970175 | H38: 1 | I38: 25 | J38: AC_HIGH_(22-49kW) | K38: =FALSE() -> FALSE
A39: 313946 | B39: IOCl Balaji Petroleum - Tata Power | C39: Sulthan Bathery | D39: Kerala | E39: IN | F39: 11.660943 | G39: 76.240023 | H39: 1 | I39: 30 | J39: AC_HIGH_(22-49kW) | K39: =FALSE() -> FALSE
A40: 313945 | B40: Hotel Saugandhika Charging Station - Tata Power | C40: Meenangadi | D40: Kerala | E40: IN | F40: 11.659328 | G40: 76.207185 | H40: 2 | I40: 60 | J40: DC_FAST_(50-149kW) | K40: =TRUE() -> TRUE
A41: 313944 | B41: TML Marina Motors Pvt. Ltd. Kalpetta - Tata Power | C41: Kalpetta | D41: Kerala | E41: IN | F41: 11.637353 | G41: 76.094685 | H41: 1 | I41: 30 | J41: AC_HIGH_(22-49kW) | K41: =FALSE() -> FALSE
A42: 313943 | B42: Taj Wayanad Resort and Spa- Tata Power | C42: Padinjarathara | D42: Kerala | E42: IN | F42: 11.657633 | G42: 75.960432 | H42: 2 | I42: 30 | J42: AC_HIGH_(22-49kW) | K42: =FALSE() -> FALSE
A43: 313942 | B43: KVR Dream Vehicles Thalassery - Tata Power | C43: Thalassery | D43: Kerala | E43: IN | F43: 11.761734 | G43: 75.509068 | H43: 1 | I43: 30 | J43: AC_HIGH_(22-49kW) | K43: =FALSE() -> FALSE
A44: 313941 | B44: IOCL - MK Petroleum - Tata Power | C44: Thazhe Chovva | D44: Kerala | E44: IN | F44: 11.86015 | G44: 75.414341 | H44: 1 | I44: 30 | J44: AC_HIGH_(22-49kW) | K44: =FALSE() -> FALSE
A45: 313940 | B45: KVR Dream Vehicles Service Centre - Tata Power | C45: Iritty | D45: Kerala | E45: IN | F45: 11.990686 | G45: 75.658022 | H45: 1 | I45: 30 | J45: AC_HIGH_(22-49kW) | K45: =FALSE() -> FALSE
A46: 313925 | B46: KVR Dream Vehicle - Tata Power | C46: Nadal | D46: Kerala | E46: IN | F46: 11.832857 | G46: 75.426442 | H46: 2 | I46: 25 | J46: AC_HIGH_(22-49kW) | K46: =FALSE() -> FALSE
A47: 313924 | B47: Tata.ev KVR Dreams Kannur - Tata Power | C47: Kannur | D47: Kerala | E47: IN | F47: 11.86083 | G47: 75.411868 | H47: 2 | I47: 30 | J47: AC_HIGH_(22-49kW) | K47: =FALSE() -> FALSE
A48: 313923 | B48: KVR Dream Vehicles Service Center - Tata Power | C48: Payyanur | D48: Kerala | E48: IN | F48: 12.120003 | G48: 75.217555 | H48: 1 | I48: 30 | J48: AC_HIGH_(22-49kW) | K48: =FALSE() -> FALSE
A49: 313922 | B49: V-Net Shopping Complex - Tata Power | C49: Payyannur | D49: Kerala | E49: IN | F49: 12.175048 | G49: 75.193433 | H49: 1 | I49: 30 | J49: AC_HIGH_(22-49kW) | K49: =FALSE() -> FALSE
A50: 313921 | B50: Taj Bekkal - Tata Power | C50: Bekkal | D50: Kerala | E50: IN | F50: 12.423383 | G50: 75.014755 | H50: 2 | I50: 7.4 | J50: AC_L1_(<7.5kW) | K50: =FALSE() -> FALSE
A51: 313920 | B51: TML KVR Dream Vehicles EVCS - Tata Power | C51: Kasaragod | D51: Kerala | E51: IN | F51: 12.513454 | G51: 75.027123 | H51: 1 | I51: 30 | J51: AC_HIGH_(22-49kW) | K51: =FALSE() -> FALSE
A52: 313919 | B52: IOCL Top Fuels Karanthakkad Charging Station - Tata Power | C52: Kasaragod | D52: Kerala | E52: IN | F52: 12.509408 | G52: 74.986111 | H52: 1 | I52: 30 | J52: AC_HIGH_(22-49kW) | K52: =FALSE() -> FALSE
A53: 313918 | B53: Eco Charge Hub - GO EC | C53: Thiruvananthapuram | D53: Kerala | E53: IN | F53: 8.353209 | G53: 77.05379 | H53: 3 | I53: 60 | J53: DC_FAST_(50-149kW) | K53: =TRUE() -> TRUE
A54: 313917 | B54: Rajco EVCS - GO EC | C54: Neyyattinkara | D54: Kerala | E54: IN | F54: 8.394253 | G54: 77.088729 | H54: 4 | I54: 30 | J54: AC_HIGH_(22-49kW) | K54: =FALSE() -> FALSE
A55: 313916 | B55: Appolo Dimora Hotel EVCS - GO EC | C55: Thiruvananthapuram | D55: Kerala | E55: IN | F55: 8.488661 | G55: 76.950752 | H55: 1 | I55: 30 | J55: AC_HIGH_(22-49kW) | K55: =FALSE() -> FALSE
A56: 313915 | B56: Lulu International Mall EVCS - GO EC | C56: Thiruvananthapuram | D56: Kerala | E56: IN | F56: 8.515263 | G56: 76.898158 | H56: 11 | I56: 60 | J56: DC_FAST_(50-149kW) | K56: =TRUE() -> TRUE
A57: 313914 | B57: Trivandrum UST Campus EVCS - GO EC | C57: Thiruvananthapuram | D57: Kerala | E57: IN | F57: 8.539993 | G57: 76.884425 | H57: 6 | I57: 7.4 | J57: AC_L1_(<7.5kW) | K57: =FALSE() -> FALSE
A58: 313913 | B58: Karthika Residency Hotel EVCS - GO EC | C58: Karette | D58: Kerala | E58: IN | F58: 8.728846 | G58: 76.898448 | H58: 2 | I58: 80 | J58: DC_FAST_(50-149kW) | K58: =TRUE() -> TRUE
A59: 313912 | B59: KKP Renewables EVCS - GO EC | C59: Karette | D59: Kerala | E59: IN | F59: 8.734523 | G59: 76.898016 | H59: 1 | I59: 30 | J59: AC_HIGH_(22-49kW) | K59: =FALSE() -> FALSE
A60: 313911 | B60: Aeron EVCS - GO EC | C60: Attingal | D60: Kerala | E60: IN | F60: 8.686808 | G60: 76.824022 | H60: 2 | I60: 30 | J60: AC_HIGH_(22-49kW) | K60: =FALSE() -> FALSE
A61: 313910 | B61: Zenith EVCS - GO EC | C61: Attingal | D61: Kerala | E61: IN | F61: 8.733068 | G61: 76.810647 | H61: 1 | I61: 30 | J61: AC_HIGH_(22-49kW) | K61: =FALSE() -> FALSE
A62: 313909 | B62: Orion Plaza EVCS - GO EC | C62: Chadayamangalam | D62: Kerala | E62: IN | F62: 8.863427 | G62: 76.871208 | H62: 3 | I62: 60 | J62: DC_FAST_(50-149kW) | K62: =TRUE() -> TRUE
A63: 313908 | B63: Power Up EVCS - GO EC | C63: Varkala | D63: Kerala | E63: IN | F63: 8.749086 | G63: 76.705819 | H63: 2 | I63: 25 | J63: AC_HIGH_(22-49kW) | K63: =FALSE() -> FALSE
A64: 313907 | B64: Green Planet EVCS - GO EC | C64: Kottarakkara | D64: Kerala | E64: IN | F64: 8.982143 | G64: 76.80933 | H64: 2 | I64: 30 | J64: AC_HIGH_(22-49kW) | K64: =FALSE() -> FALSE
A65: 313906 | B65: RK EVCS - GO EC | C65: Kundara | D65: Kerala | E65: IN | F65: 8.948247 | G65: 76.646247 | H65: 2 | I65: 30 | J65: AC_HIGH_(22-49kW) | K65: =FALSE() -> FALSE
A66: 313905 | B66: SK EVCS - GO EC | C66: Pathanapuram | D66: Kerala | E66: IN | F66: 9.070992 | G66: 76.856311 | H66: 2 | I66: 25 | J66: AC_HIGH_(22-49kW) | K66: =FALSE() -> FALSE
A67: 313904 | B67: Erathu Motors EVCS - GO EC | C67: Puthoor | D67: Kerala | E67: IN | F67: 9.051367 | G67: 76.703247 | H67: 2 | I67: 30 | J67: AC_HIGH_(22-49kW) | K67: =FALSE() -> FALSE
A68: 313903 | B68: Vrindavan EVCS - GO EC | C68: Inchakkad | D68: Kerala | E68: IN | F68: 9.045128 | G68: 76.7736 | H68: 4 | I68: 60 | J68: DC_FAST_(50-149kW) | K68: =TRUE() -> TRUE
A69: 313902 | B69: JB Power EVCS - GO EC | C69: Adoor | D69: Kerala | E69: IN | F69: 9.116847 | G69: 76.745112 | H69: 3 | I69: 60 | J69: DC_FAST_(50-149kW) | K69: =TRUE() -> TRUE
A70: 313901 | B70: Peninsula Park Residency EVCS - GO EC | C70: Adoor | D70: Kerala | E70: IN | F70: 9.145306 | G70: 76.765858 | H70: 1 | I70: 30 | J70: AC_HIGH_(22-49kW) | K70: =FALSE() -> FALSE
A71: 313900 | B71: Green Earth - GO EC | C71: Adoor | D71: Kerala | E71: IN | F71: 9.153564 | G71: 76.735544 | H71: 3 | I71: 60 | J71: DC_FAST_(50-149kW) | K71: =TRUE() -> TRUE
A72: 313899 | B72: Sparkzone EVCS - GO EC | C72: Kayamkulam | D72: Kerala | E72: IN | F72: 9.145795 | G72: 76.459363 | H72: 2 | I72: 25 | J72: AC_HIGH_(22-49kW) | K72: =FALSE() -> FALSE
A73: 313898 | B73: Zufo EVCS | C73: Karunagappalli | D73: Kerala | E73: IN | F73: 9.132307 | G73: 76.513858 | H73: 1 | I73: 25 | J73: AC_HIGH_(22-49kW) | K73: =FALSE() -> FALSE
A74: 313897 | B74: Cartist - GO EC | C74: Kayamkulam | D74: Kerala | E74: IN | F74: 9.18474 | G74: 76.490297 | H74: 4 | I74: 60 | J74: DC_FAST_(50-149kW) | K74: =TRUE() -> TRUE
A75: 313896 | B75: V Volte EVCS - GO EC | C75: Haripad | D75: Kerala | E75: IN | F75: 9.289001 | G75: 76.456536 | H75: 2 | I75: 25 | J75: AC_HIGH_(22-49kW) | K75: =FALSE() -> FALSE
A76: 313895 | B76: Anjaly EVCS - GO EC | C76: Omallor | D76: Kerala | E76: IN | F76: 9.246935 | G76: 76.757308 | H76: 2 | I76: 30 | J76: AC_HIGH_(22-49kW) | K76: =FALSE() -> FALSE
A77: 313894 | B77: Evergreen Continental EVCS - GO EC | C77: Pathanamthitta | D77: Kerala | E77: IN | F77: 9.263777 | G77: 76.785435 | H77: 1 | I77: 30 | J77: AC_HIGH_(22-49kW) | K77: =FALSE() -> FALSE
A78: 313893 | B78: Quik Energy EVCS - GO EC | C78: Chengannur | D78: Kerala | E78: IN | F78: 9.311533 | G78: 76.622721 | H78: 4 | I78: 60 | J78: DC_FAST_(50-149kW) | K78: =TRUE() -> TRUE
A79: 313892 | B79: Amrutham Auto Care EVCS - GO EC | C79: Chengannur | D79: Kerala | E79: IN | F79: 9.342145 | G79: 76.598488 | H79: 2 | I79: 30 | J79: AC_HIGH_(22-49kW) | K79: =FALSE() -> FALSE
A80: 313891 | B80: Changanassery Immaculate Mary EVCS | C80: Changanassery | D80: Kerala | E80: IN | F80: 9.45986 | G80: 76.555184 | H80: 2 | I80: 25 | J80: AC_HIGH_(22-49kW) | K80: =FALSE() -> FALSE
A81: 313890 | B81: Calvarymount Jerry Plaza | C81: Alliyar | D81: Kerala | E81: IN | F81: 9.806942 | G81: 77.04794 | H81: 1 | I81: 30 | J81: AC_HIGH_(22-49kW) | K81: =FALSE() -> FALSE
A82: 313889 | B82: Westgate Inn EVCS - GO EC | C82: Kattappana | D82: Kerala | E82: IN | F82: 9.747617 | G82: 77.105418 | H82: 1 | I82: 25 | J82: AC_HIGH_(22-49kW) | K82: =FALSE() -> FALSE
A83: 313888 | B83: GO EC Charging Station | C83: Idukki | D83: Kerala | E83: IN | F83: 9.665399 | G83: 77.160847 | H83: 2 | I83: 30 | J83: AC_HIGH_(22-49kW) | K83: =FALSE() -> FALSE
A84: 313887 | B84: Sora EVCS - GO EC | C84: Kumali | D84: Kerala | E84: IN | F84: 9.614446 | G84: 77.15391 | H84: 2 | I84: 30 | J84: AC_HIGH_(22-49kW) | K84: =FALSE() -> FALSE
A85: 313886 | B85: Open Kitchen EVCS - GO EC | C85: Kuttikkanam | D85: Kerala | E85: IN | F85: 9.580204 | G85: 76.970612 | H85: 3 | I85: 60 | J85: DC_FAST_(50-149kW) | K85: =TRUE() -> TRUE
A86: 313885 | B86: Nandanam EVCS - GO EC | C86: Kodungoor | D86: Kerala | E86: IN | F86: 9.567075 | G86: 76.706094 | H86: 1 | I86: 30 | J86: AC_HIGH_(22-49kW) | K86: =FALSE() -> FALSE
A87: 313884 | B87: Clay Art Cafe - GO EC | C87: Ponkunnam | D87: Kerala | E87: IN | F87: 9.566379 | G87: 76.741608 | H87: 2 | I87: 25 | J87: AC_HIGH_(22-49kW) | K87: =FALSE() -> FALSE
A88: 313883 | B88: GO Green EVCS - GO EC | C88: Anthikkad | D88: Kerala | E88: IN | F88: 9.754 | G88: 76.701279 | H88: 1 | I88: 30 | J88: AC_HIGH_(22-49kW) | K88: =FALSE() -> FALSE
A89: 313882 | B89: Nila's Magestic Arcade | C89: Kidangoor | D89: Kerala | E89: IN | F89: 9.683248 | G89: 76.609754 | H89: 1 | I89: 30 | J89: AC_HIGH_(22-49kW) | K89: =FALSE() -> FALSE
A90: 313881 | B90: Ettumanur Skylight EVCS - GO EC | C90: Ettumanoor | D90: Kerala | E90: IN | F90: 9.668172 | G90: 76.575379 | H90: 3 | I90: 60 | J90: DC_FAST_(50-149kW) | K90: =TRUE() -> TRUE
A91: 313880 | B91: Chaithanya Hospital EVCS - GO EC | C91: Kuravilangad | D91: Kerala | E91: IN | F91: 9.761924 | G91: 76.564723 | H91: 2 | I91: 25 | J91: AC_HIGH_(22-49kW) | K91: =FALSE() -> FALSE
A92: 313879 | B92: Manjoor Beeza Clubhouse EVCS - GO EC | C92: Manjoor | D92: Kerala | E92: IN | F92: 9.727579 | G92: 76.520388 | H92: 1 | I92: 30 | J92: AC_HIGH_(22-49kW) | K92: =FALSE() -> FALSE
A93: 313878 | B93: Kalladanthiyil EVCS - GO EC | C93: Neendoor | D93: Kerala | E93: IN | F93: 9.683337 | G93: 76.505594 | H93: 2 | I93: 30 | J93: AC_HIGH_(22-49kW) | K93: =FALSE() -> FALSE
A94: 313877 | B94: The Grand Ambassador EVCS | C94: Kottayam | D94: Kerala | E94: IN | F94: 9.589399 | G94: 76.526331 | H94: 1 | I94: 30 | J94: AC_HIGH_(22-49kW) | K94: =FALSE() -> FALSE
A95: 313876 | B95: Hotel Athira Residency EVCS - GO EC | C95: Kottayam | D95: Kerala | E95: IN | F95: 9.578259 | G95: 76.519471 | H95: 2 | I95: 80 | J95: DC_FAST_(50-149kW) | K95: =TRUE() -> TRUE
A96: 313875 | B96: Cassia Regency EVCS - GO EC | C96: Alappuzha | D96: Kerala | E96: IN | F96: 9.49017 | G96: 76.320737 | H96: 1 | I96: 30 | J96: AC_HIGH_(22-49kW) | K96: =FALSE() -> FALSE
A97: 313874 | B97: Neo Charge EVCS - GO EC | C97: Alappuzha | D97: Kerala | E97: IN | F97: 9.559497 | G97: 76.328214 | H97: 1 | I97: 30 | J97: AC_HIGH_(22-49kW) | K97: =FALSE() -> FALSE
A98: 313873 | B98: Jason Orchard Inn EVCS - GO EC | C98: Alappuzha | D98: Kerala | E98: IN | F98: 9.562575 | G98: 76.327584 | H98: 1 | I98: 30 | J98: AC_HIGH_(22-49kW) | K98: =FALSE() -> FALSE
A99: 313872 | B99: Huts Restaurant EVCS - GO EC | C99: Cherthala | D99: Kerala | E99: IN | F99: 9.683891 | G99: 76.333582 | H99: 3 | I99: 60 | J99: DC_FAST_(50-149kW) | K99: =TRUE() -> TRUE
A100: 313871 | B100: Vijaya EVCS - GO EC | C100: Kanjiramattom | D100: Kerala | E100: IN | F100: 9.85184 | G100: 76.389388 | H100: 1 | I100: 30 | J100: AC_HIGH_(22-49kW) | K100: =FALSE() -> FALSE
...

Sheet State_Summary
A1: State | B1: OCM Sites (COUNTIFS) | C1: Total Ports (SUMIFS) | D1: Avg Power kW (AVERAGEIFS) | E1: Fast-DC Sites | F1: Fast-DC Share %
A2: Kerala | B2: =COUNTIFS(OCM_Raw_Data!$D$2:$D$1181,A2) -> 454 | C2: =SUMIFS(OCM_Raw_Data!$H$2:$H$1181,OCM_Raw_Data!$D$2:$D$1181,A2) -> 1001 | D2: =IFERROR(AVERAGEIFS(OCM_Raw_Data!$I$2:$I$1181,OCM_Raw_Data!$D$2:$D$1181,A2),0) -> 38.354185 | E2: =COUNTIFS(OCM_Raw_Data!$D$2:$D$1181,A2,OCM_Raw_Data!$K$2:$K$1181,TRUE()) -> 136 | F2: =E2/B2 -> 0.29955947
A3: Karnataka | B3: =COUNTIFS(OCM_Raw_Data!$D$2:$D$1181,A3) -> 362 | C3: =SUMIFS(OCM_Raw_Data!$H$2:$H$1181,OCM_Raw_Data!$D$2:$D$1181,A3) -> 524 | D3: =IFERROR(AVERAGEIFS(OCM_Raw_Data!$I$2:$I$1181,OCM_Raw_Data!$D$2:$D$1181,A3),0) -> 52.577072 | E3: =COUNTIFS(OCM_Raw_Data!$D$2:$D$1181,A3,OCM_Raw_Data!$K$2:$K$1181,TRUE()) -> 196 | F3: =E3/B3 -> 0.54143646
A4: Tamil Nadu | B4: =COUNTIFS(OCM_Raw_Data!$D$2:$D$1181,A4) -> 182 | C4: =SUMIFS(OCM_Raw_Data!$H$2:$H$1181,OCM_Raw_Data!$D$2:$D$1181,A4) -> 208 | D4: =IFERROR(AVERAGEIFS(OCM_Raw_Data!$I$2:$I$1181,OCM_Raw_Data!$D$2:$D$1181,A4),0) -> 41.572222 | E4: =COUNTIFS(OCM_Raw_Data!$D$2:$D$1181,A4,OCM_Raw_Data!$K$2:$K$1181,TRUE()) -> 59 | F4: =E4/B4 -> 0.32417582
A5: Rajasthan | B5: =COUNTIFS(OCM_Raw_Data!$D$2:$D$1181,A5) -> 34 | C5: =SUMIFS(OCM_Raw_Data!$H$2:$H$1181,OCM_Raw_Data!$D$2:$D$1181,A5) -> 65 | D5: =IFERROR(AVERAGEIFS(OCM_Raw_Data!$I$2:$I$1181,OCM_Raw_Data!$D$2:$D$1181,A5),0) -> 30.529412 | E5: =COUNTIFS(OCM_Raw_Data!$D$2:$D$1181,A5,OCM_Raw_Data!$K$2:$K$1181,TRUE()) -> 2 | F5: =E5/B5 -> 0.058823529
A6: Delhi | B6: =COUNTIFS(OCM_Raw_Data!$D$2:$D$1181,A6) -> 30 | C6: =SUMIFS(OCM_Raw_Data!$H$2:$H$1181,OCM_Raw_Data!$D$2:$D$1181,A6) -> 53 | D6: =IFERROR(AVERAGEIFS(OCM_Raw_Data!$I$2:$I$1181,OCM_Raw_Data!$D$2:$D$1181,A6),0) -> 31.333333 | E6: =COUNTIFS(OCM_Raw_Data!$D$2:$D$1181,A6,OCM_Raw_Data!$K$2:$K$1181,TRUE()) -> 8 | F6: =E6/B6 -> 0.26666667
A7: Haryana | B7: =COUNTIFS(OCM_Raw_Data!$D$2:$D$1181,A7) -> 27 | C7: =SUMIFS(OCM_Raw_Data!$H$2:$H$1181,OCM_Raw_Data!$D$2:$D$1181,A7) -> 59 | D7: =IFERROR(AVERAGEIFS(OCM_Raw_Data!$I$2:$I$1181,OCM_Raw_Data!$D$2:$D$1181,A7),0) -> 49.518519 | E7: =COUNTIFS(OCM_Raw_Data!$D$2:$D$1181,A7,OCM_Raw_Data!$K$2:$K$1181,TRUE()) -> 11 | F7: =E7/B7 -> 0.40740741
A8: Gujarat | B8: =COUNTIFS(OCM_Raw_Data!$D$2:$D$1181,A8) -> 23 | C8: =SUMIFS(OCM_Raw_Data!$H$2:$H$1181,OCM_Raw_Data!$D$2:$D$1181,A8) -> 35 | D8: =IFERROR(AVERAGEIFS(OCM_Raw_Data!$I$2:$I$1181,OCM_Raw_Data!$D$2:$D$1181,A8),0) -> 31.18 | E8: =COUNTIFS(OCM_Raw_Data!$D$2:$D$1181,A8,OCM_Raw_Data!$K$2:$K$1181,TRUE()) -> 3 | F8: =E8/B8 -> 0.13043478
A9: Uttar Pradesh | B9: =COUNTIFS(OCM_Raw_Data!$D$2:$D$1181,A9) -> 21 | C9: =SUMIFS(OCM_Raw_Data!$H$2:$H$1181,OCM_Raw_Data!$D$2:$D$1181,A9) -> 37 | D9: =IFERROR(AVERAGEIFS(OCM_Raw_Data!$I$2:$I$1181,OCM_Raw_Data!$D$2:$D$1181,A9),0) -> 52.425 | E9: =COUNTIFS(OCM_Raw_Data!$D$2:$D$1181,A9,OCM_Raw_Data!$K$2:$K$1181,TRUE()) -> 10 | F9: =E9/B9 -> 0.47619048
A10: Maharashtra | B10: =COUNTIFS(OCM_Raw_Data!$D$2:$D$1181,A10) -> 16 | C10: =SUMIFS(OCM_Raw_Data!$H$2:$H$1181,OCM_Raw_Data!$D$2:$D$1181,A10) -> 33 | D10: =IFERROR(AVERAGEIFS(OCM_Raw_Data!$I$2:$I$1181,OCM_Raw_Data!$D$2:$D$1181,A10),0) -> 58.071429 | E10: =COUNTIFS(OCM_Raw_Data!$D$2:$D$1181,A10,OCM_Raw_Data!$K$2:$K$1181,TRUE()) -> 10 | F10: =E10/B10 -> 0.625
A11: Telangana | B11: =COUNTIFS(OCM_Raw_Data!$D$2:$D$1181,A11) -> 7 | C11: =SUMIFS(OCM_Raw_Data!$H$2:$H$1181,OCM_Raw_Data!$D$2:$D$1181,A11) -> 8 | D11: =IFERROR(AVERAGEIFS(OCM_Raw_Data!$I$2:$I$1181,OCM_Raw_Data!$D$2:$D$1181,A11),0) -> 49.066667 | E11: =COUNTIFS(OCM_Raw_Data!$D$2:$D$1181,A11,OCM_Raw_Data!$K$2:$K$1181,TRUE()) -> 2 | F11: =E11/B11 -> 0.28571429
A12: Goa | B12: =COUNTIFS(OCM_Raw_Data!$D$2:$D$1181,A12) -> 6 | C12: =SUMIFS(OCM_Raw_Data!$H$2:$H$1181,OCM_Raw_Data!$D$2:$D$1181,A12) -> 6 | D12: =IFERROR(AVERAGEIFS(OCM_Raw_Data!$I$2:$I$1181,OCM_Raw_Data!$D$2:$D$1181,A12),0) -> 50 | E12: =COUNTIFS(OCM_Raw_Data!$D$2:$D$1181,A12,OCM_Raw_Data!$K$2:$K$1181,TRUE()) -> 4 | F12: =E12/B12 -> 0.66666667
A13: West Bengal | B13: =COUNTIFS(OCM_Raw_Data!$D$2:$D$1181,A13) -> 6 | C13: =SUMIFS(OCM_Raw_Data!$H$2:$H$1181,OCM_Raw_Data!$D$2:$D$1181,A13) -> 6 | D13: =IFERROR(AVERAGEIFS(OCM_Raw_Data!$I$2:$I$1181,OCM_Raw_Data!$D$2:$D$1181,A13),0) -> 42 | E13: =COUNTIFS(OCM_Raw_Data!$D$2:$D$1181,A13,OCM_Raw_Data!$K$2:$K$1181,TRUE()) -> 2 | F13: =E13/B13 -> 0.33333333
A14: Andhra Pradesh | B14: =COUNTIFS(OCM_Raw_Data!$D$2:$D$1181,A14) -> 3 | C14: =SUMIFS(OCM_Raw_Data!$H$2:$H$1181,OCM_Raw_Data!$D$2:$D$1181,A14) -> 4 | D14: =IFERROR(AVERAGEIFS(OCM_Raw_Data!$I$2:$I$1181,OCM_Raw_Data!$D$2:$D$1181,A14),0) -> 70 | E14: =COUNTIFS(OCM_Raw_Data!$D$2:$D$1181,A14,OCM_Raw_Data!$K$2:$K$1181,TRUE()) -> 1 | F14: =E14/B14 -> 0.33333333
A15: TOTAL / NATIONAL AVG | B15: =SUM(B2:B14) -> 1171 | C15: =SUM(C2:C14) -> 2039 | D15: =AVERAGE(D2:D14) -> 45.894449 | E15: =SUM(E2:E14) -> 444 | F15: =E15/B15 -> 0.37916311
A17: Note: this sheet reflects OCM (crowdsourced) coverage only — see Official_vs_Crowdsourced for real installed-base comparison.

Sheet Official_vs_Crowdsourced
A1: State | B1: Official PIB EVCS (as of 01-Aug-2025) | C1: OCM-Mapped Sites | D1: OCM Coverage % of Official | E1: Source
A2: Karnataka | B2: 6097 | C2: =COUNTIFS(OCM_Raw_Data!$D$2:$D$1181,A2) -> 362 | D2: =C2/B2 -> 0.059373462 | E2: Sec.3.1, PIB PRID 2154127 (via TeslaVolts Table 3.1)
A3: Maharashtra | B3: 4155 | C3: =COUNTIFS(OCM_Raw_Data!$D$2:$D$1181,A3) -> 16 | D3: =C3/B3 -> 0.0038507822 | E3: Sec.3.1, PIB PRID 2154127 (via TeslaVolts Table 3.1)
A4: Uttar Pradesh | B4: 2326 | C4: =COUNTIFS(OCM_Raw_Data!$D$2:$D$1181,A4) -> 21 | D4: =C4/B4 -> 0.0090283749 | E4: PIB PRID 2154127, Annexure A (direct, MoP)
A5: Delhi | B5: 1967 | C5: =COUNTIFS(OCM_Raw_Data!$D$2:$D$1181,A5) -> 30 | D5: =C5/B5 -> 0.015251652 | E5: Sec.3.1, PIB PRID 2154127 (via TeslaVolts Table 3.1)
A6: Tamil Nadu | B6: 1781 | C6: =COUNTIFS(OCM_Raw_Data!$D$2:$D$1181,A6) -> 182 | D6: =C6/B6 -> 0.10218978 | E6: Sec.3.1, PIB PRID 2154127 (via TeslaVolts Table 3.1)
A7: Rajasthan | B7: 1531 | C7: =COUNTIFS(OCM_Raw_Data!$D$2:$D$1181,A7) -> 34 | D7: =C7/B7 -> 0.022207707 | E7: Sec.3.1, PIB PRID 2154127 (via TeslaVolts Table 3.1)
A8: Kerala | B8: 1392 | C8: =COUNTIFS(OCM_Raw_Data!$D$2:$D$1181,A8) -> 454 | D8: =C8/B8 -> 0.32614943 | E8: Sec.3.1, PIB PRID 2154127 (via TeslaVolts Table 3.1)
A9: TOTAL (these 7 states) | B9: =SUM(B2:B8) -> 19249 | C9: =SUM(C2:C8) -> 1099 | D9: =C9/B9 -> 0.057093875
A11: National context (not state-summable):
A12: Official national public EVCS, 01-Aug-2025 (PIB PRID 2154127) | B12: 29277
A13: Total OCM-mapped India sites (this workbook, cleaned) | B13: =COUNTA(OCM_Raw_Data!A2:A1181) -> 1179
A14: Implied national OCM coverage % | B14: =B13/B12 -> 0.04027052
A16: Interpretation: yellow-filled cells are hardcoded official figures sourced from PIB — cite these for any real headline claim about India's charging network. OCM coverage % measures ONLY how discoverable a state's stations are on the crowdsourced OpenChargeMap platform, not infrastructure quality or adequacy.

Sheet Demand_Supply_Gap
A1: State | B1: Official EVCS (Aug-2025) | C1: EV Sales, CY2025 (units) | D1: Share of Natl EV Sales 2025 | E1: New EVs Sold per Station (2025) | F1: Stress Rank (1=worst)
A2: Uttar Pradesh | B2: 2326 | C2: 400000 | D2: 0.18 | E2: =C2/B2 -> 171.96905 | F2: =RANK(E2,$E$2:$E$4,0) -> 1
A3: Maharashtra | B3: 4155 | C3: 266000 | D3: 0.12 | E3: =C3/B3 -> 64.019254 | F3: =RANK(E3,$E$2:$E$4,0) -> 2
A4: Karnataka | B4: 6097 | C4: 173000 | E4: =C4/B4 -> 28.37461 | F4: =RANK(E4,$E$2:$E$4,0) -> 3
A7: Sources
A8: Uttar Pradesh: PIB PRID2154127 (stations); Navionyx/Vahan-derived, 2025 (sales, 18% natl share)
A9: Maharashtra: PIB PRID2154127 (stations); Navionyx/Vahan-derived, 2025 (sales, 12% natl share)
A10: Karnataka: PIB PRID2154127 (stations); Deccan Herald, FY24-25 EV sales (2W+3W+4W), citing MoRTH/RTO data
A13: National context
A14: Cumulative EVs registered nationally, as of 08-Feb-2025 (e-Vahan / PIB PRID2101635) | B14: 5675000
A15: Public EVCS nationally, as of 01-Aug-2025 (PIB PRID2154127) | B15: 29277
A16: Implied national installed-base ratio (cumulative EVs per station — NOT an annual-flow metric, differs from cols above) | B16: =B14/B15 -> 193.83817
A18: Read this table as: how many NEW EVs were sold in 2025 for every EXISTING public station — a stress/pressure metric on the current network, not a literal 'cars per plug' figure (each EV doesn't need its own charger). Higher = more pressure on existing infrastructure.

Sheet Recommendations
A1: Strategic recommendations — where to prioritize new public charging investment
A3: 1. Uttar Pradesh is the single highest-pressure state in the network.
A4: UP sold 18% of India's 2025 EV volume (~4 lakh units, mostly e-2W/e-3W) but holds only 8% of the top-7 states' charging stations (2,326 of 29,277 nationally). At ~172 new EVs sold per existing station in 2025 alone, UP's stress ratio is roughly 6x Karnataka's (~28:1). Because UP's EV mix is dominated by two/three-wheelers that mostly charge at home or via battery swapping, this is less acute for range anxiety than the raw ratio implies — but it's still the state where new public DC/AC capacity should be added first for four-wheeler and fleet segments.
A6: 2. Karnataka's density masks a Bengaluru-only story.
A7: 6,097 stations sounds dominant, but public reporting (Deccan Herald, Aug 2025) puts the count much lower at city/state-department level (468 in one district-level count), and industry sources note utilization outside Bengaluru is thin. Don't read 'most stations' as 'most accessible' — recommend a district-level follow-up study before assuming Karnataka's infrastructure gap is closed.
A9: 3. Crowdsourced platforms (Google Maps/OSM-linked apps) undercount India's real network by ~96%.
A10: OCM shows 1,178 mapped stations against an official 29,277 — a coverage gap that matters directly for any GTM plan built on 'where do EV drivers currently look for chargers.' A charge-point operator or app relying on OCM/OSM data alone is working from a dataset that's missing the vast majority of real stations, mostly OMC-installed sites (IOCL alone operates 7,928) that haven't been crowd-mapped.
A12: 4. Fast-DC share is a Karnataka/Maharashtra/UP story, not a national one.
A13: In the OCM-mapped subset, fast-DC share is 54% in Karnataka and 63% in Maharashtra but under 6% in Rajasthan and 13% in Gujarat. If the goal is highway-corridor readiness (PM E-DRIVE's 50-corridor target), Rajasthan and Gujarat's AC-heavy networks are the weaker links despite reasonable total station counts.
A15: 5. Data quality is itself a finding.
A16: The raw crowdsourced dataset contained a 1,000,000 kW power rating on a single-port site (obvious data entry error) and 10+ garbled/misspelled state labels. Any pipeline consuming OCM data directly needs validation rules on power_kw (cap at physically plausible values, e.g. 400 kW) and a state-name canonicalization step before it's usable for reporting.
